Workbook

Sheet CUSTOS ANUAIS
A2: Bem-vindos ao Simulador Financeiro Ânima Nest. Uma ferramenta auxiliadora e parte integrante na elaboração de um primeiro Plano de Negócios Empreendedor. Este simulador simpllifica e automatiza a realização dos cálculos financeiros, gerando projeções de resultados e indicadores de viabilidade fundamentais para a tomada de decisão do empreendedor iniciante. O objetivo principal dessa ferramenta é estabelecer uma conexão economicamente viável sobre questões relacionadas a faturamento, custos, despesas, lucro, capacidade de honrar compromissos, etc. Além disso, o jovem empreendedor poderá realizar análise de cenários, simulando o impacto de eventuais variações nos resultados da empresa, decidindo investimentos com muito mais segurança. Informações: 1. Tenha em mãos valores estimados necessários para a realização do empreendimento, tais como: a) quantidade de dias que a empresa funicionará por mês; b) gastos com aquisição de máquinas, computadores, licenças, mobiliário, etc; c) Despesas fixas mensais como, aluguel, água, energia elétrica, seguro, internet e telefone, etc; d) quantidade de pessoal inicial; Com essas informações à mão, antes de preencher os campos Investidores e Receita, preencha os valores Custos Fixos, Colaboradores, Custos variáveis e Investimento. 2. Caso o seu modelo de negócio não dependa de um determinado item, coloque-o o valor como R$ 0,00. Evite apagar a célula. 3. No campo Colaboradores, adicione o cargo pertinente e o custo com salário mensal, incluindo o seu, da equipe e de demais colaboradores externo. Caso tenha mais colaboradores, adicione outras células abaixo de "Colaborador 4". O salário mínimo vigente no ano de 2025 é de R$ 1.509,00. 4. Em 2025, o limite de faturamento anual para MEI é de R$81.000,00. Faturamentos acima desse valor, a empresa se enquadra no Modelo Simples Nacional, na qual depende de um contador. VAMOS COMEÇAR?
A4: NOME DA EMPRESA | B4: Cidade Alerta | K4: DATA DO PROJETO | M4: 46169
A6: NOME DOS INTEGRANTES | B6: Ramon Vinicius do Nascimento Lucena-Caio Alex Donato Leitão-Jonatha Henrique Machado Espinoza
A8: Receita | B8: Janeiro | C8: Fevereiro | D8: Março | E8: Abril | F8: Maio | G8: Junho | H8: Julho | I8: Agosto | J8: Setembro | K8: Outubro | L8: Novembro | M8: Dezembro | N8: Total Anual
A9: Produto / Serviço 1 | B9: 0 | C9: 0 | D9: 0 | E9: 0 | F9: 0 | G9: 0 | H9: 0 | I9: 0 | J9: 0 | K9: 0 | L9: 0 | M9: 0 | N9: =SUM(B9:M9) -> 0
A10: Produto / Serviço 2 | B10: 0 | C10: 0 | D10: 0 | E10: 0 | F10: 0 | G10: 0 | H10: 0 | I10: 0 | J10: 0 | K10: 0 | L10: 0 | M10: 0 | N10: =SUM(B10:M10) -> 0
A11: Outras fontes de receita | B11: 0 | C11: 0 | D11: 0 | E11: 0 | F11: 0 | G11: 0 | H11: 0 | I11: 0 | J11: 0 | K11: 0 | L11: 0 | M11: 0 | N11: =SUM(B11:M11) -> 0
A12: Receita Total | B12: =SUM(B9:B11) -> 0 | C12: =SUM(C9:C11) -> 0 | D12: =SUM(D9:D11) -> 0 | E12: =SUM(E9:E11) -> 0 | F12: =SUM(F9:F11) -> 0 | G12: =SUM(G9:G11) -> 0 | H12: =SUM(H9:H11) -> 0 | I12: =SUM(I9:I11) -> 0 | ... M12: =SUM(M9:M11) -> 0 | N12: =SUM(B12:M12) -> 0
A14: Custos Fixos | B14: Janeiro | C14: Fevereiro | D14: Março | E14: Abril | F14: Maio | G14: Junho | H14: Julho | I14: Agosto | J14: Setembro | K14: Outubro | L14: Novembro | M14: Dezembro | N14: Total Anual
A15: Àgua | B15: 30 | C15: 30 | D15: 30 | E15: 30 | F15: 30 | G15: 30 | H15: 30 | I15: 30 | J15: 30 | K15: 30 | L15: 30 | M15: 30 | N15: =SUM(B15:M15) -> 360
A16: Energia elétrica | B16: 150 | C16: 150 | D16: 150 | E16: 150 | F16: 150 | G16: 150 | H16: 150 | I16: 150 | J16: 150 | K16: 150 | L16: 150 | M16: 150 | N16: =SUM(B16:M16) -> 1800
A17: Internet e Telefone | B17: 60 | C17: 60 | D17: 60 | E17: 60 | F17: 60 | G17: 60 | H17: 60 | I17: 60 | J17: 60 | K17: 60 | L17: 60 | M17: 60 | N17: =SUM(B17:M17) -> 720
A18: Aluguel | B18: 0 | C18: 0 | D18: 0 | E18: 0 | F18: 0 | G18: 0 | H18: 0 | I18: 0 | J18: 0 | K18: 0 | L18: 0 | M18: 0 | N18: =SUM(B18:M18) -> 0
A19: Deslocamento / Combustível | B19: 0 | C19: 0 | D19: 0 | E19: 0 | F19: 0 | G19: 0 | H19: 0 | I19: 0 | J19: 0 | K19: 0 | L19: 0 | M19: 0 | N19: =SUM(B19:M19) -> 0
A20: Materiais de escritório | B20: 0 | C20: 0 | D20: 0 | E20: 0 | F20: 0 | G20: 0 | H20: 0 | I20: 0 | J20: 0 | K20: 0 | L20: 0 | M20: 0 | N20: =SUM(B20:M20) -> 0
A21: Extras | B21: 0 | C21: 0 | D21: 0 | E21: 0 | F21: 0 | G21: 0 | H21: 0 | I21: 0 | J21: 0 | K21: 0 | L21: 0 | M21: 0 | N21: =SUM(B21:M21) -> 0
A22: Fixo Total | B22: =SUM(B15:B21) -> 240 | C22: =SUM(C15:C21) -> 240 | D22: =SUM(D15:D21) -> 240 | E22: =SUM(E15:E21) -> 240 | F22: =SUM(F15:F21) -> 240 | G22: =SUM(G15:G21) -> 240 | H22: =SUM(H15:H21) -> 240 | I22: =SUM(I15:I21) -> 240 | ... M22: =SUM(M15:M21) -> 240 | N22: =SUM(B22:M22) -> 2880
A24: Colaboradores | B24: Janeiro | C24: Fevereiro | D24: Março | E24: Abril | F24: Maio | G24: Junho | H24: Julho | I24: Agosto | J24: Setembro | K24: Outubro | L24: Novembro | M24: Dezembro | N24: Total Anual
A25: Colaborador 1 | B25: 1590 | C25: 1590 | D25: 1590 | E25: 1590 | F25: 1590 | G25: 1590 | H25: 1590 | I25: 1590 | J25: 1590 | K25: 1590 | L25: 1590 | M25: 1590 | N25: =SUM(B25:M25) -> 19080
A26: Colaborador 2 | B26: 1590 | C26: 1590 | D26: 1590 | E26: 1590 | F26: 1590 | G26: 1590 | H26: 1590 | I26: 1590 | J26: 1590 | K26: 1590 | L26: 1590 | M26: 1590 | N26: =SUM(B26:M26) -> 19080
A27: Colaborador 3 | B27: 1590 | C27: 1590 | D27: 1590 | E27: 1590 | F27: 1590 | G27: 1590 | H27: 1590 | I27: 1590 | J27: 1590 | K27: 1590 | L27: 1590 | M27: 1590 | N27: =SUM(B27:M27) -> 19080
A28: Colaborador 4 | B28: 0 | C28: 0 | D28: 0 | E28: 0 | F28: 0 | G28: 0 | H28: 0 | I28: 0 | J28: 0 | K28: 0 | L28: 0 | M28: 0 | N28: =SUM(B28:M28) -> 0
A29: Colaborador Total | B29: =SUM(B25:B28) -> 4770 | C29: =SUM(C25:C28) -> 4770 | D29: =SUM(D25:D28) -> 4770 | E29: =SUM(E25:E28) -> 4770 | F29: =SUM(F25:F28) -> 4770 | G29: =SUM(G25:G28) -> 4770 | H29: =SUM(H25:H28) -> 4770 | I29: =SUM(I25:I28) -> 4770 | ... N29: =SUM(N25:N28) -> 57240
A31: Custos Variáveis | B31: Janeiro | C31: Fevereiro | D31: Março | E31: Abril | F31: Maio | G31: Junho | H31: Julho | I31: Agosto | J31: Setembro | K31: Outubro | L31: Novembro | M31: Dezembro | N31: Total Anual
A32: Imposto (consolidado) | B32: 0 | C32: 0 | D32: 0 | E32: 0 | F32: 0 | G32: 0 | H32: 0 | I32: 0 | J32: 0 | K32: 0 | L32: 0 | M32: 0 | N32: =SUM(B32:M32) -> 0
A33: DAS* | B33: 0 | C33: 0 | D33: 0 | E33: 0 | F33: 0 | G33: 0 | H33: 0 | I33: 0 | J33: 0 | K33: 0 | L33: 0 | M33: 0 | N33: =SUM(B33:M33) -> 0
A34: Mão de obra terceirizada | B34: 0 | C34: 0 | D34: 0 | E34: 0 | F34: 0 | G34: 0 | H34: 0 | I34: 0 | J34: 0 | K34: 0 | L34: 0 | M34: 0 | N34: =SUM(B34:M34) -> 0
A35: Variável Total | B35: =SUM(B32:B34) -> 0 | C35: =SUM(C32:C34) -> 0 | D35: =SUM(D32:D34) -> 0 | E35: =SUM(E32:E34) -> 0 | F35: =SUM(F32:F34) -> 0 | G35: =SUM(G32:G34) -> 0 | H35: =SUM(H32:H34) -> 0 | I35: =SUM(I32:I34) -> 0 | ... M35: =SUM(M32:M34) -> 0 | N35: =SUM(B35:M35) -> 0
A37: Investimentos | B37: Janeiro | C37: Fevereiro | D37: Março | E37: Abril | F37: Maio | G37: Junho | H37: Julho | I37: Agosto | J37: Setembro | K37: Outubro | L37: Novembro | M37: Dezembro | N37: Total Anual
A38: Computador | B38: 4000 | C38: 0 | D38: 0 | E38: 0 | F38: 0 | G38: 0 | H38: 0 | I38: 0 | J38: 0 | K38: 0 | L38: 0 | M38: 0 | N38: =SUM(B38:M38) -> 4000
A39: Periféricos | B39: 100 | C39: 0 | D39: 0 | E39: 0 | F39: 0 | G39: 0 | H39: 0 | I39: 0 | J39: 0 | K39: 0 | L39: 0 | M39: 0 | N39: =SUM(B39:M39) -> 100
A40: Mobiliário | B40: 0 | C40: 0 | D40: 0 | E40: 0 | F40: 0 | G40: 0 | H40: 0 | I40: 0 | J40: 0 | K40: 0 | L40: 0 | M40: 0 | N40: =SUM(B40:M40) -> 0
A41: Extras | B41: 0 | C41: 0 | D41: 0 | E41: 0 | F41: 0 | G41: 0 | H41: 0 | I41: 0 | J41: 0 | K41: 0 | L41: 0 | M41: 0 | N41: =SUM(B41:M41) -> 0
A42: Investimento Total | B42: =SUM(B38:B41) -> 4100 | C42: =SUM(C38:C41) -> 0 | D42: =SUM(D38:D41) -> 0 | E42: =SUM(E38:E41) -> 0 | F42: =SUM(F38:F41) -> 0 | G42: =SUM(G38:G41) -> 0 | H42: =SUM(H38:H41) -> 0 | I42: =SUM(I38:I41) -> 0 | ... M42: =SUM(M38:M41) -> 0 | N42: =SUM(B42:M42) -> 4100
A44: Saldo | B44: Janeiro | C44: Fevereiro | D44: Março | E44: Abril | F44: Maio | G44: Junho | H44: Julho | I44: Agosto | J44: Setembro | K44: Outubro | L44: Novembro | M44: Dezembro | N44: Total Anual
A45: Saldo Total | B45: =SUM(B12-B22-B29-B35-B42) -> -9110 | C45: =SUM(C12-C22-C29-C35-C42) -> -5010 | D45: =SUM(D12-D22-D29-D35-D42) -> -5010 | E45: =SUM(E12-E22-E29-E35-E42) -> -5010 | F45: =SUM(F12-F22-F29-F35-F42) -> -5010 | G45: =SUM(G12-G22-G29-G35-G42) -> -5010 | H45: =SUM(H12-H22-H29-H35-H42) -> -5010 | I45: =SUM(I12-I22-I29-I35-I42) -> -5010 | ... N45: =SUM(N12-N22-N29-N35-N42) -> -64220
A47: Lucro Líquido | B47: Janeiro | C47: Fevereiro | D47: Março | E47: Abril | F47: Maio | G47: Junho | H47: Julho | I47: Agosto | J47: Setembro | K47: Outubro | L47: Novembro | M47: Dezembro | N47: Lucro Líq. Anual
A48: Caixa Total | B48: =B45 -> -9110 | C48: =C45+B48 -> -14120 | D48: =D45+C48 -> -19130 | E48: =E45+D48 -> -24140 | F48: =F45+E48 -> -29150 | G48: =G45+F48 -> -34160 | H48: =H45+G48 -> -39170 | I48: =I45+H48 -> -44180 | J48: =J45+I48 -> -49190 | ... M48: =M45+L48 -> -64220 | N48: =M48 -> -64220

Sheet RESULTADOS
A1: Demonstrativo de Resultado
F3: =('CUSTOS ANUAIS'!B4) -> Cidade Alerta | G3: =IF(N8>81000,"se enquadra no modelo Simples Nacional", "se enquadra no modelo MEI") -> se enquadra no modelo MEI
A5: Receita | B5: Janeiro | C5: Fevereiro | D5: Março | E5: Abril | F5: Maio | G5: Junho | H5: Julho | I5: Agosto | J5: Setembro | K5: Outubro | L5: Novembro | M5: Dezembro | N5: Total | O5: Comparação
A6: Projeto 1 | B6: ='CUSTOS ANUAIS'!B9 -> 0 | C6: ='CUSTOS ANUAIS'!C9 -> 0 | D6: ='CUSTOS ANUAIS'!D9 -> 0 | E6: ='CUSTOS ANUAIS'!E9 -> 0 | F6: ='CUSTOS ANUAIS'!F9 -> 0 | G6: ='CUSTOS ANUAIS'!G9 -> 0 | H6: ='CUSTOS ANUAIS'!H9 -> 0 | I6: ='CUSTOS ANUAIS'!I9 -> 0 | ... M6: ='CUSTOS ANUAIS'!M9 -> 0 | N6: =SUM(B6:M6) -> 0 | O6: =+N6/N$8 -> #DIV/0!
A7: Projeto 2 | B7: ='CUSTOS ANUAIS'!B10 -> 0 | C7: ='CUSTOS ANUAIS'!C10 -> 0 | D7: ='CUSTOS ANUAIS'!D10 -> 0 | E7: ='CUSTOS ANUAIS'!E10 -> 0 | F7: ='CUSTOS ANUAIS'!F10 -> 0 | G7: ='CUSTOS ANUAIS'!G10 -> 0 | H7: ='CUSTOS ANUAIS'!H10 -> 0 | I7: ='CUSTOS ANUAIS'!I10 -> 0 | ... M7: ='CUSTOS ANUAIS'!M10 -> 0 | N7: =SUM(B7:M7) -> 0 | O7: =+N7/N$8 -> #DIV/0!
A8: Receita Total | B8: =SUM(B6:B7) -> 0 | C8: =SUM(C6:C7) -> 0 | D8: =SUM(D6:D7) -> 0 | E8: =SUM(E6:E7) -> 0 | F8: =SUM(F6:F7) -> 0 | G8: =SUM(G6:G7) -> 0 | H8: =SUM(H6:H7) -> 0 | I8: =SUM(I6:I7) -> 0 | ... M8: =SUM(M6:M7) -> 0 | N8: =SUM(B8:M8) -> 0 | O8: 1
A10: Custos Variáveis | B10: Janeiro | C10: Fevereiro | D10: Março | E10: Abril | F10: Maio | G10: Junho | H10: Julho | I10: Agosto | J10: Setembro | K10: Outubro | L10: Novembro | M10: Dezembro | N10: Total | O10: Comparação
A11: IPTU | B11: ='CUSTOS ANUAIS'!B32 -> 0 | C11: ='CUSTOS ANUAIS'!C32 -> 0 | D11: ='CUSTOS ANUAIS'!D32 -> 0 | E11: ='CUSTOS ANUAIS'!E32 -> 0 | F11: ='CUSTOS ANUAIS'!F32 -> 0 | G11: ='CUSTOS ANUAIS'!G32 -> 0 | H11: ='CUSTOS ANUAIS'!H32 -> 0 | I11: ='CUSTOS ANUAIS'!I32 -> 0 | ... M11: ='CUSTOS ANUAIS'!M32 -> 0 | N11: =SUM(B11:M11) -> 0 | O11: =+N11/N$14 -> #DIV/0!
A12: DAS | B12: ='CUSTOS ANUAIS'!B33 -> 0 | C12: ='CUSTOS ANUAIS'!C33 -> 0 | D12: ='CUSTOS ANUAIS'!D33 -> 0 | E12: ='CUSTOS ANUAIS'!E33 -> 0 | F12: ='CUSTOS ANUAIS'!F33 -> 0 | G12: ='CUSTOS ANUAIS'!G33 -> 0 | H12: ='CUSTOS ANUAIS'!H33 -> 0 | I12: ='CUSTOS ANUAIS'!I33 -> 0 | ... M12: ='CUSTOS ANUAIS'!M33 -> 0 | N12: =SUM(B12:M12) -> 0 | O12: =+N12/N$14 -> #DIV/0!
A13: Mão de obra terceirizada | B13: ='CUSTOS ANUAIS'!B34 -> 0 | C13: ='CUSTOS ANUAIS'!C34 -> 0 | D13: ='CUSTOS ANUAIS'!D34 -> 0 | E13: ='CUSTOS ANUAIS'!E34 -> 0 | F13: ='CUSTOS ANUAIS'!F34 -> 0 | G13: ='CUSTOS ANUAIS'!G34 -> 0 | H13: ='CUSTOS ANUAIS'!H34 -> 0 | I13: ='CUSTOS ANUAIS'!I34 -> 0 | ... M13: ='CUSTOS ANUAIS'!M34 -> 0 | N13: =SUM(B13:M13) -> 0 | O13: =+N13/N$14 -> #DIV/0!
A14: Variáveis Totais | B14: =SUM(B11:B13) -> 0 | C14: =SUM(C11:C13) -> 0 | D14: =SUM(D11:D13) -> 0 | E14: =SUM(E11:E13) -> 0 | F14: =SUM(F11:F13) -> 0 | G14: =SUM(G11:G13) -> 0 | H14: =SUM(H11:H13) -> 0 | I14: =SUM(I11:I13) -> 0 | ... M14: =SUM(M11:M13) -> 0 | N14: =SUM(B14:M14) -> 0 | O14: 1
A16: Margem de Contribuição | B16: Janeiro | C16: Fevereiro | D16: Março | E16: Abril | F16: Maio | G16: Junho | H16: Julho | I16: Agosto | J16: Setembro | K16: Outubro | L16: Novembro | M16: Dezembro | N16: Total | O16: Comparação
A17: Margem total | B17: =B8-B14 -> 0 | C17: =C8-C14 -> 0 | D17: =D8-D14 -> 0 | E17: =E8-E14 -> 0 | F17: =F8-F14 -> 0 | G17: =G8-G14 -> 0 | H17: =H8-H14 -> 0 | I17: =I8-I14 -> 0 | ... M17: =M8-M14 -> 0 | N17: =SUM(B17:M17) -> 0
A18: Porcentagem | B18: =B17/B8 -> #DIV/0! | C18: =C17/C8 -> #DIV/0! | D18: =D17/D8 -> #DIV/0! | E18: =E17/E8 -> #DIV/0! | F18: =F17/F8 -> #DIV/0! | G18: =G17/G8 -> #DIV/0! | H18: =H17/H8 -> #DIV/0! | I18: =I17/I8 -> #DIV/0! | ... N18: =N17/N8 -> #DIV/0!
A20: Custos Fixos | B20: Janeiro | C20: Fevereiro | D20: Março | E20: Abril | F20: Maio | G20: Junho | H20: Julho | I20: Agosto | J20: Setembro | K20: Outubro | L20: Novembro | M20: Dezembro | N20: Total | O20: Comparação
A21: Fixos Totais | B21: ='CUSTOS ANUAIS'!B22 -> 240 | C21: ='CUSTOS ANUAIS'!C22 -> 240 | D21: ='CUSTOS ANUAIS'!D22 -> 240 | E21: ='CUSTOS ANUAIS'!E22 -> 240 | F21: ='CUSTOS ANUAIS'!F22 -> 240 | G21: ='CUSTOS ANUAIS'!G22 -> 240 | H21: ='CUSTOS ANUAIS'!H22 -> 240 | I21: ='CUSTOS ANUAIS'!I22 -> 240 | ... M21: ='CUSTOS ANUAIS'!M22 -> 240 | N21: =SUM(B21:M21) -> 2880 | O21: 1
A23: Resultado Operacional | B23: Janeiro | C23: Fevereiro | D23: Março | E23: Abril | F23: Maio | G23: Junho | H23: Julho | I23: Agosto | J23: Setembro | K23: Outubro | L23: Novembro | M23: Dezembro | N23: Total | O23: Comparação
A24: Resultado Total | B24: =B17-B21 -> -240 | C24: =C17-C21 -> -240 | D24: =D17-D21 -> -240 | E24: =E17-E21 -> -240 | F24: =F17-F21 -> -240 | G24: =G17-G21 -> -240 | H24: =H17-H21 -> -240 | I24: =I17-I21 -> -240 | ... M24: =M17-M21 -> -240 | N24: =SUM(B24:M24) -> -2880
A25: Porcentagem | B25: =B24/B8 -> #DIV/0! | C25: =C24/C8 -> #DIV/0! | D25: =D24/D8 -> #DIV/0! | E25: =E24/E8 -> #DIV/0! | F25: =F24/F8 -> #DIV/0! | G25: =G24/G8 -> #DIV/0! | H25: =H24/H8 -> #DIV/0! | I25: =I24/I8 -> #DIV/0! | ... N25: =N24/N8 -> #DIV/0!
A27: Custos Totais | B27: Janeiro | C27: Fevereiro | D27: Março | E27: Abril | F27: Maio | G27: Junho | H27: Julho | I27: Agosto | J27: Setembro | K27: Outubro | L27: Novembro | M27: Dezembro | N27: Total | O27: Comparação
A28: Totais | B28: =SUM('CUSTOS ANUAIS'!B22,'CUSTOS ANUAIS'!B29,'CUSTOS ANUAIS'!B35,'CUSTOS ANUAIS'!B42) -> 9110 | C28: =SUM('CUSTOS ANUAIS'!C22,'CUSTOS ANUAIS'!C29,'CUSTOS ANUAIS'!C35,'CUSTOS ANUAIS'!C42) -> 5010 | D28: =SUM('CUSTOS ANUAIS'!D22,'CUSTOS ANUAIS'!D29,'CUSTOS ANUAIS'!D35,'CUSTOS ANUAIS'!D42) -> 5010 | E28: =SUM('CUSTOS ANUAIS'!E22,'CUSTOS ANUAIS'!E29,'CUSTOS ANUAIS'!E35,'CUSTOS ANUAIS'!E42) -> 5010 | F28: =SUM('CUSTOS ANUAIS'!F22,'CUSTOS ANUAIS'!F29,'CUSTOS ANUAIS'!F35,'CUSTOS ANUAIS'!F42) -> 5010 | G28: =SUM('CUSTOS ANUAIS'!G22,'CUSTOS ANUAIS'!G29,'CUSTOS ANUAIS'!G35,'CUSTOS ANUAIS'!G42) -> 5010 | H28: =SUM('CUSTOS ANUAIS'!H22,'CUSTOS ANUAIS'!H29,'CUSTOS ANUAIS'!H35,'CUSTOS ANUAIS'!H42) -> 5010 | I28: =SUM('CUSTOS ANUAIS'!I22,'CUSTOS ANUAIS'!I29,'CUSTOS ANUAIS'!I35,'CUSTOS ANUAIS'!I42) -> 5010 | ... M28: =SUM('CUSTOS ANUAIS'!M22,'CUSTOS ANUAIS'!M29,'CUSTOS ANUAIS'!M35,'CUSTOS ANUAIS'!M42) -> 5010 | N28: =SUM(B28:M28) -> 64220 | O28: 1
A30: Ponto de Equilibrio Contábil | B30: Janeiro | C30: Fevereiro | D30: Março | E30: Abril | F30: Maio | G30: Junho | H30: Julho | I30: Agosto | J30: Setembro | K30: Outubro | L30: Novembro | M30: Dezembro | N30: Total | O30: Comparação
A31: Valor Total | B31: =B21/B17 -> #DIV/0! | C31: =C21/C17 -> #DIV/0! | D31: =D21/D17 -> #DIV/0! | E31: =E21/E17 -> #DIV/0! | F31: =F21/F17 -> #DIV/0! | G31: =G21/G17 -> #DIV/0! | H31: =H21/H17 -> #DIV/0! | I31: =I21/I17 -> #DIV/0! | ... N31: =N21/N17 -> #DIV/0! | O31: 1
